activerest/__init__.py
activerest/resources.py
activerest-0.0.5.dist-info/LICENSE.txt
activerest-0.0.5.dist-info/METADATA
activerest-0.0.5.dist-info/RECORD
activerest-0.0.5.dist-info/WHEEL
activerest-0.0.5.dist-info/top_level.txt
